LICENSE
MANIFEST.in
README.rst
setup.py
funfactory/__init__.py
funfactory/admin.py
funfactory/cmd.py
funfactory/context_processors.py
funfactory/helpers.py
funfactory/log.py
funfactory/log_settings.py
funfactory/manage.py
funfactory/middleware.py
funfactory/models.py
funfactory/monkeypatches.py
funfactory/settings_base.py
funfactory/urlresolvers.py
funfactory/utils.py
funfactory.egg-info/PKG-INFO
funfactory.egg-info/SOURCES.txt
funfactory.egg-info/dependency_links.txt
funfactory.egg-info/entry_points.txt
funfactory.egg-info/top_level.txt