Metadata-Version: 1.1
Name: funfactory
Version: 2.3.0
Summary: Mozilla's Django app skeleton.
Home-page: https://github.com/mozilla/funfactory
Author: Kumar McMillan and contributors
Author-email: UNKNOWN
License: BSD License
Platform: UNKNOWN
Classifier: Development Status :: 5 - Production/Stable
Classifier: Environment :: Web Environment
Classifier: Framework :: Django
Classifier: Intended Audience :: Developers
Classifier: License :: OSI Approved :: BSD License
Classifier: Natural Language :: English
Classifier: Operating System :: OS Independent
Classifier: Programming Language :: Python
Classifier: Programming Language :: Python :: 2.6
Classifier: Programming Language :: Python :: 2.7
